{
  "measurements": [
    {
      "date": "2022-05-01",
      "weight": 78.9,
      "muscle_mass": 35.9,
      "fat_mass": 16,
      "bmi": 24.4,
      "body_fat_percent": 20.3,
      "bmr": 1728,
      "inbody_score": 77,
      "visceral_fat_level": null
    },
    {
      "date": "2022-06-01",
      "weight": 77.7,
      "muscle_mass": 35.5,
      "fat_mass": 15.4,
      "bmi": 24,
      "body_fat_percent": 19.9,
      "bmr": 1715,
      "inbody_score": 77,
      "visceral_fat_level": null
    },
    {
      "date": "2022-06-18",
      "weight": 78.4,
      "muscle_mass": 35.9,
      "fat_mass": 15.3,
      "bmi": 24.2,
      "body_fat_percent": 19.5,
      "bmr": 1734,
      "inbody_score": 78,
      "visceral_fat_level": null
    },
    {
      "date": "2022-07-07",
      "weight": 78,
      "muscle_mass": 36.1,
      "fat_mass": 14.6,
      "bmi": 24.1,
      "body_fat_percent": 18.8,
      "bmr": 1738,
      "inbody_score": 79,
      "visceral_fat_level": null
    },
    {
      "date": "2022-07-15",
      "weight": 77,
      "muscle_mass": 35.4,
      "fat_mass": 14.6,
      "bmi": 23.8,
      "body_fat_percent": 19,
      "bmr": 1718,
      "inbody_score": 78,
      "visceral_fat_level": null
    },
    {
      "date": "2022-07-31",
      "weight": 78,
      "muscle_mass": 36.6,
      "fat_mass": 14,
      "bmi": 24.1,
      "body_fat_percent": 18,
      "bmr": 1752,
      "inbody_score": null,
      "visceral_fat_level": null
    },
    {
      "date": "2022-08-08",
      "weight": 79.1,
      "muscle_mass": 37,
      "fat_mass": 14.4,
      "bmi": 24.4,
      "body_fat_percent": 18.2,
      "bmr": 1768,
      "inbody_score": 81,
      "visceral_fat_level": null
    },
    {
      "date": "2022-09-02",
      "weight": 78.5,
      "muscle_mass": 36.1,
      "fat_mass": 15,
      "bmi": 24.2,
      "body_fat_percent": 19.2,
      "bmr": 1741,
      "inbody_score": 79,
      "visceral_fat_level": null
    },
    {
      "date": "2022-10-25",
      "weight": 78.5,
      "muscle_mass": 35.8,
      "fat_mass": 15.8,
      "bmi": 24.2,
      "body_fat_percent": 20.2,
      "bmr": 1724,
      "inbody_score": 77,
      "visceral_fat_level": null
    },
    {
      "date": "2022-11-01",
      "weight": 79.2,
      "muscle_mass": 35.2,
      "fat_mass": 17.3,
      "bmi": 24.7,
      "body_fat_percent": 21.8,
      "bmr": 1708,
      "inbody_score": 76,
      "visceral_fat_level": null
    },
    {
      "date": "2022-11-28",
      "weight": 78.9,
      "muscle_mass": 34.8,
      "fat_mass": 17.6,
      "bmi": 24.6,
      "body_fat_percent": 22.3,
      "bmr": 1695,
      "inbody_score": 75,
      "visceral_fat_level": null
    },
    {
      "date": "2022-12-12",
      "weight": 78.6,
      "muscle_mass": 35.4,
      "fat_mass": 16.3,
      "bmi": 24.5,
      "body_fat_percent": 20.7,
      "bmr": 1716,
      "inbody_score": 77,
      "visceral_fat_level": null
    },
    {
      "date": "2022-12-29",
      "weight": 78.3,
      "muscle_mass": 34.6,
      "fat_mass": 17.2,
      "bmi": 24.4,
      "body_fat_percent": 22,
      "bmr": 1690,
      "inbody_score": 75,
      "visceral_fat_level": null
    },
    {
      "date": "2023-01-30",
      "weight": 78.1,
      "muscle_mass": 35.2,
      "fat_mass": 16.3,
      "bmi": 24.1,
      "body_fat_percent": 20.8,
      "bmr": 1705,
      "inbody_score": 76,
      "visceral_fat_level": null
    },
    {
      "date": "2023-02-06",
      "weight": 78.7,
      "muscle_mass": 36.6,
      "fat_mass": 14.7,
      "bmi": 24.3,
      "body_fat_percent": 18.7,
      "bmr": 1752,
      "inbody_score": 80,
      "visceral_fat_level": null
    },
    {
      "date": "2023-05-17",
      "weight": 77.1,
      "muscle_mass": 35.1,
      "fat_mass": 15.5,
      "bmi": 23.8,
      "body_fat_percent": 20.1,
      "bmr": 1700,
      "inbody_score": 76,
      "visceral_fat_level": null
    },
    {
      "date": "2023-06-05",
      "weight": 77.9,
      "muscle_mass": 35.2,
      "fat_mass": 15.9,
      "bmi": 24,
      "body_fat_percent": 20.5,
      "bmr": 1708,
      "inbody_score": 76,
      "visceral_fat_level": null
    },
    {
      "date": "2023-06-06",
      "weight": 77.7,
      "muscle_mass": 35.4,
      "fat_mass": 15.7,
      "bmi": 24,
      "body_fat_percent": 20.2,
      "bmr": 1710,
      "inbody_score": 77,
      "visceral_fat_level": null
    },
    {
      "date": "2023-06-11",
      "weight": 77.5,
      "muscle_mass": 35.7,
      "fat_mass": 15,
      "bmi": 23.9,
      "body_fat_percent": 19.4,
      "bmr": 1719,
      "inbody_score": 78,
      "visceral_fat_level": null
    },
    {
      "date": "2023-06-25",
      "weight": 76,
      "muscle_mass": 35.4,
      "fat_mass": 14.1,
      "bmi": 23.5,
      "body_fat_percent": 18.6,
      "bmr": 1707,
      "inbody_score": 78,
      "visceral_fat_level": null
    },
    {
      "date": "2023-07-03",
      "weight": 78.8,
      "muscle_mass": 36.6,
      "fat_mass": 14.5,
      "bmi": 24.3,
      "body_fat_percent": 18.4,
      "bmr": 1759,
      "inbody_score": 81,
      "visceral_fat_level": null
    },
    {
      "date": "2023-07-07",
      "weight": 78.1,
      "muscle_mass": 36.1,
      "fat_mass": 14.8,
      "bmi": 24.1,
      "body_fat_percent": 19,
      "bmr": 1737,
      "inbody_score": 79,
      "visceral_fat_level": null
    },
    {
      "date": "2023-07-14",
      "weight": 78.4,
      "muscle_mass": 36.6,
      "fat_mass": 14.2,
      "bmi": 24.2,
      "body_fat_percent": 18.1,
      "bmr": 1757,
      "inbody_score": 81,
      "visceral_fat_level": null
    },
    {
      "date": "2023-07-17",
      "weight": 77.4,
      "muscle_mass": 36,
      "fat_mass": 14.5,
      "bmi": 23.9,
      "body_fat_percent": 18.7,
      "bmr": 1730,
      "inbody_score": 79,
      "visceral_fat_level": null
    },
    {
      "date": "2023-07-22",
      "weight": 78.1,
      "muscle_mass": 36.6,
      "fat_mass": 14.2,
      "bmi": 24.1,
      "body_fat_percent": 18.2,
      "bmr": 1750,
      "inbody_score": 80,
      "visceral_fat_level": null
    },
    {
      "date": "2023-08-01",
      "weight": 78.9,
      "muscle_mass": 37,
      "fat_mass": 14.3,
      "bmi": 24.4,
      "body_fat_percent": 18.1,
      "bmr": 1766,
      "inbody_score": 81,
      "visceral_fat_level": null
    },
    {
      "date": "2023-08-04",
      "weight": 79.7,
      "muscle_mass": 36.8,
      "fat_mass": 15.3,
      "bmi": 24.6,
      "body_fat_percent": 19.2,
      "bmr": 1761,
      "inbody_score": 80,
      "visceral_fat_level": null
    },
    {
      "date": "2023-08-13",
      "weight": 80.2,
      "muscle_mass": 37.2,
      "fat_mass": 15.1,
      "bmi": 24.8,
      "body_fat_percent": 18.9,
      "bmr": 1775,
      "inbody_score": 81,
      "visceral_fat_level": null
    },
    {
      "date": "2023-08-20",
      "weight": 78.9,
      "muscle_mass": 36.2,
      "fat_mass": 15.7,
      "bmi": 24.4,
      "body_fat_percent": 19.9,
      "bmr": 1736,
      "inbody_score": 78,
      "visceral_fat_level": null
    },
    {
      "date": "2023-09-14",
      "weight": 80.2,
      "muscle_mass": 37.6,
      "fat_mass": 14.4,
      "bmi": 24.8,
      "body_fat_percent": 18,
      "bmr": 1791,
      "inbody_score": 82,
      "visceral_fat_level": null
    },
    {
      "date": "2023-09-21",
      "weight": 80.6,
      "muscle_mass": 37.7,
      "fat_mass": 14.7,
      "bmi": 24.9,
      "body_fat_percent": 18.2,
      "bmr": 1794,
      "inbody_score": 82,
      "visceral_fat_level": null
    },
    {
      "date": "2023-09-29",
      "weight": 79.9,
      "muscle_mass": 37.4,
      "fat_mass": 14.6,
      "bmi": 24.7,
      "body_fat_percent": 18.3,
      "bmr": 1780,
      "inbody_score": 82,
      "visceral_fat_level": null
    },
    {
      "date": "2023-10-09",
      "weight": 81.9,
      "muscle_mass": 37.6,
      "fat_mass": 16.2,
      "bmi": 25.3,
      "body_fat_percent": 19.8,
      "bmr": 1790,
      "inbody_score": 81,
      "visceral_fat_level": null
    },
    {
      "date": "2023-10-21",
      "weight": 80.7,
      "muscle_mass": 37.4,
      "fat_mass": 15.3,
      "bmi": 24.9,
      "body_fat_percent": 19,
      "bmr": 1783,
      "inbody_score": 81,
      "visceral_fat_level": null
    },
    {
      "date": "2023-11-18",
      "weight": 80.5,
      "muscle_mass": 37.7,
      "fat_mass": 14.3,
      "bmi": 24.8,
      "body_fat_percent": 17.8,
      "bmr": 1799,
      "inbody_score": 83,
      "visceral_fat_level": null
    },
    {
      "date": "2023-11-26",
      "weight": 81.4,
      "muscle_mass": 38,
      "fat_mass": 14.8,
      "bmi": 25.1,
      "body_fat_percent": 18.2,
      "bmr": 1808,
      "inbody_score": 83,
      "visceral_fat_level": null
    },
    {
      "date": "2023-12-03",
      "weight": 81.3,
      "muscle_mass": 37.6,
      "fat_mass": 15.5,
      "bmi": 25.1,
      "body_fat_percent": 19.1,
      "bmr": 1791,
      "inbody_score": 81,
      "visceral_fat_level": null
    },
    {
      "date": "2023-12-10",
      "weight": 80.7,
      "muscle_mass": 37.6,
      "fat_mass": 14.9,
      "bmi": 24.9,
      "body_fat_percent": 18.4,
      "bmr": 1792,
      "inbody_score": 82,
      "visceral_fat_level": null
    },
    {
      "date": "2023-12-31",
      "weight": 80.9,
      "muscle_mass": 37.8,
      "fat_mass": 14.7,
      "bmi": 25,
      "body_fat_percent": 18.1,
      "bmr": 1800,
      "inbody_score": 83,
      "visceral_fat_level": null
    },
    {
      "date": "2024-01-12",
      "weight": 79.5,
      "muscle_mass": 37.5,
      "fat_mass": 13.9,
      "bmi": 24.5,
      "body_fat_percent": 17.4,
      "bmr": 1788,
      "inbody_score": 83,
      "visceral_fat_level": null
    },
    {
      "date": "2024-01-20",
      "weight": 79.9,
      "muscle_mass": 37.5,
      "fat_mass": 14.2,
      "bmi": 24.7,
      "body_fat_percent": 17.8,
      "bmr": 1789,
      "inbody_score": 83,
      "visceral_fat_level": null
    },
    {
      "date": "2024-01-30",
      "weight": 78.7,
      "muscle_mass": 36.9,
      "fat_mass": 14.1,
      "bmi": 24.3,
      "body_fat_percent": 17.9,
      "bmr": 1765,
      "inbody_score": 81,
      "visceral_fat_level": null
    },
    {
      "date": "2024-03-04",
      "weight": 79.1,
      "muscle_mass": 36.4,
      "fat_mass": 15.4,
      "bmi": 24.4,
      "body_fat_percent": 19.4,
      "bmr": 1747,
      "inbody_score": 79,
      "visceral_fat_level": null
    },
    {
      "date": "2024-03-15",
      "weight": 80.5,
      "muscle_mass": 38.2,
      "fat_mass": 13.8,
      "bmi": 24.8,
      "body_fat_percent": 17.1,
      "bmr": 1811,
      "inbody_score": 84,
      "visceral_fat_level": null
    },
    {
      "date": "2024-03-29",
      "weight": 80.1,
      "muscle_mass": 37.4,
      "fat_mass": 14.7,
      "bmi": 24.7,
      "body_fat_percent": 18.3,
      "bmr": 1784,
      "inbody_score": 82,
      "visceral_fat_level": null
    },
    {
      "date": "2024-04-11",
      "weight": 81.1,
      "muscle_mass": 37.8,
      "fat_mass": 14.7,
      "bmi": 25,
      "body_fat_percent": 18.1,
      "bmr": 1805,
      "inbody_score": 83,
      "visceral_fat_level": null
    },
    {
      "date": "2024-04-16",
      "weight": 80.3,
      "muscle_mass": 37.3,
      "fat_mass": 15.1,
      "bmi": 24.8,
      "body_fat_percent": 18.9,
      "bmr": 1777,
      "inbody_score": 81,
      "visceral_fat_level": null
    },
    {
      "date": "2024-04-30",
      "weight": 80.8,
      "muscle_mass": 37.8,
      "fat_mass": 14.7,
      "bmi": 24.9,
      "body_fat_percent": 18.2,
      "bmr": 1797,
      "inbody_score": 82,
      "visceral_fat_level": null
    },
    {
      "date": "2024-05-04",
      "weight": 81,
      "muscle_mass": 37.9,
      "fat_mass": 14.7,
      "bmi": 25,
      "body_fat_percent": 18.1,
      "bmr": 1803,
      "inbody_score": 83,
      "visceral_fat_level": null
    },
    {
      "date": "2024-05-13",
      "weight": 80.8,
      "muscle_mass": 37.9,
      "fat_mass": 14.5,
      "bmi": 24.9,
      "body_fat_percent": 18,
      "bmr": 1802,
      "inbody_score": 83,
      "visceral_fat_level": null
    },
    {
      "date": "2024-05-16",
      "weight": 80.9,
      "muscle_mass": 38,
      "fat_mass": 14.5,
      "bmi": 25,
      "body_fat_percent": 17.9,
      "bmr": 1805,
      "inbody_score": 83,
      "visceral_fat_level": null
    },
    {
      "date": "2024-06-01",
      "weight": 79.9,
      "muscle_mass": 37.5,
      "fat_mass": 14.5,
      "bmi": 24.7,
      "body_fat_percent": 18.2,
      "bmr": 1783,
      "inbody_score": 82,
      "visceral_fat_level": null
    },
    {
      "date": "2024-06-09",
      "weight": 81.3,
      "muscle_mass": 38.3,
      "fat_mass": 14.2,
      "bmi": 25.1,
      "body_fat_percent": 17.5,
      "bmr": 1819,
      "inbody_score": 84,
      "visceral_fat_level": null
    },
    {
      "date": "2024-06-17",
      "weight": 80.7,
      "muscle_mass": 38,
      "fat_mass": 14.4,
      "bmi": 24.9,
      "body_fat_percent": 17.8,
      "bmr": 1803,
      "inbody_score": 83,
      "visceral_fat_level": null
    },
    {
      "date": "2024-06-21",
      "weight": 80.3,
      "muscle_mass": 38.1,
      "fat_mass": 13.7,
      "bmi": 24.8,
      "body_fat_percent": 17,
      "bmr": 1809,
      "inbody_score": 84,
      "visceral_fat_level": null
    },
    {
      "date": "2024-06-29",
      "weight": 81.1,
      "muscle_mass": 37.7,
      "fat_mass": 15,
      "bmi": 25,
      "body_fat_percent": 18.5,
      "bmr": 1797,
      "inbody_score": 82,
      "visceral_fat_level": null
    },
    {
      "date": "2024-07-02",
      "weight": 80.9,
      "muscle_mass": 37.4,
      "fat_mass": 15.4,
      "bmi": 25,
      "body_fat_percent": 19.1,
      "bmr": 1784,
      "inbody_score": 81,
      "visceral_fat_level": null
    },
    {
      "date": "2024-07-15",
      "weight": 79.8,
      "muscle_mass": 37.1,
      "fat_mass": 14.7,
      "bmi": 24.6,
      "body_fat_percent": 18.4,
      "bmr": 1777,
      "inbody_score": 81,
      "visceral_fat_level": null
    },
    {
      "date": "2024-07-26",
      "weight": 80.3,
      "muscle_mass": 37.4,
      "fat_mass": 15,
      "bmi": 24.8,
      "body_fat_percent": 18.7,
      "bmr": 1780,
      "inbody_score": 81,
      "visceral_fat_level": null
    },
    {
      "date": "2024-08-01",
      "weight": 80.7,
      "muscle_mass": 38.2,
      "fat_mass": 14,
      "bmi": 24.9,
      "body_fat_percent": 17.4,
      "bmr": 1810,
      "inbody_score": 84,
      "visceral_fat_level": null
    },
    {
      "date": "2024-08-09",
      "weight": 80.5,
      "muscle_mass": 38.3,
      "fat_mass": 13.5,
      "bmi": 24.8,
      "body_fat_percent": 16.8,
      "bmr": 1816,
      "inbody_score": 85,
      "visceral_fat_level": null
    },
    {
      "date": "2024-09-03",
      "weight": 78.2,
      "muscle_mass": 36.9,
      "fat_mass": 13.7,
      "bmi": 24.1,
      "body_fat_percent": 17.5,
      "bmr": 1763,
      "inbody_score": 82,
      "visceral_fat_level": null
    },
    {
      "date": "2024-09-08",
      "weight": 79.5,
      "muscle_mass": 36.3,
      "fat_mass": 15.8,
      "bmi": 24.5,
      "body_fat_percent": 19.9,
      "bmr": 1746,
      "inbody_score": 79,
      "visceral_fat_level": null
    },
    {
      "date": "2024-09-26",
      "weight": 80.3,
      "muscle_mass": 37.4,
      "fat_mass": 14.9,
      "bmi": 24.8,
      "body_fat_percent": 18.6,
      "bmr": 1783,
      "inbody_score": 81,
      "visceral_fat_level": null
    },
    {
      "date": "2024-10-22",
      "weight": 79.5,
      "muscle_mass": 36.9,
      "fat_mass": 14.6,
      "bmi": 24.5,
      "body_fat_percent": 18.4,
      "bmr": 1772,
      "inbody_score": 81,
      "visceral_fat_level": null
    },
    {
      "date": "2024-11-01",
      "weight": 80.3,
      "muscle_mass": 36.3,
      "fat_mass": 16.8,
      "bmi": 24.8,
      "body_fat_percent": 20.9,
      "bmr": 1741,
      "inbody_score": 77,
      "visceral_fat_level": null
    },
    {
      "date": "2024-11-19",
      "weight": 81.9,
      "muscle_mass": 37,
      "fat_mass": 17.1,
      "bmi": 25.3,
      "body_fat_percent": 20.9,
      "bmr": 1769,
      "inbody_score": 79,
      "visceral_fat_level": null
    },
    {
      "date": "2024-12-03",
      "weight": 82,
      "muscle_mass": 37.7,
      "fat_mass": 15.9,
      "bmi": 25.3,
      "body_fat_percent": 19.4,
      "bmr": 1798,
      "inbody_score": 81,
      "visceral_fat_level": null
    },
    {
      "date": "2024-12-15",
      "weight": 81.3,
      "muscle_mass": 36.4,
      "fat_mass": 17.5,
      "bmi": 25.1,
      "body_fat_percent": 21.5,
      "bmr": 1749,
      "inbody_score": 77,
      "visceral_fat_level": null
    },
    {
      "date": "2024-12-31",
      "weight": 82.3,
      "muscle_mass": 37.6,
      "fat_mass": 16.3,
      "bmi": 25.4,
      "body_fat_percent": 19.7,
      "bmr": 1797,
      "inbody_score": 81,
      "visceral_fat_level": null
    },
    {
      "date": "2025-01-06",
      "weight": 80.5,
      "muscle_mass": 37.5,
      "fat_mass": 14.8,
      "bmi": 24.8,
      "body_fat_percent": 18.4,
      "bmr": 1789,
      "inbody_score": 82,
      "visceral_fat_level": null
    },
    {
      "date": "2025-01-10",
      "weight": 80.2,
      "muscle_mass": 36.8,
      "fat_mass": 15.7,
      "bmi": 24.8,
      "body_fat_percent": 19.5,
      "bmr": 1764,
      "inbody_score": 80,
      "visceral_fat_level": null
    },
    {
      "date": "2025-01-20",
      "weight": 80.5,
      "muscle_mass": 37.1,
      "fat_mass": 15.5,
      "bmi": 24.8,
      "body_fat_percent": 19.3,
      "bmr": 1774,
      "inbody_score": 80,
      "visceral_fat_level": null
    },
    {
      "date": "2025-01-29",
      "weight": 79.7,
      "muscle_mass": 37.1,
      "fat_mass": 14.9,
      "bmi": 24.6,
      "body_fat_percent": 18.7,
      "bmr": 1770,
      "inbody_score": 81,
      "visceral_fat_level": null
    },
    {
      "date": "2025-01-31",
      "weight": 80.7,
      "muscle_mass": 36.8,
      "fat_mass": 16.4,
      "bmi": 24.9,
      "body_fat_percent": 20.3,
      "bmr": 1759,
      "inbody_score": 79,
      "visceral_fat_level": null
    },
    {
      "date": "2025-02-23",
      "weight": 80.5,
      "muscle_mass": 37,
      "fat_mass": 15.6,
      "bmi": 24.8,
      "body_fat_percent": 19.4,
      "bmr": 1772,
      "inbody_score": 80,
      "visceral_fat_level": null
    },
    {
      "date": "2025-03-14",
      "weight": 81,
      "muscle_mass": 37.8,
      "fat_mass": 14.5,
      "bmi": 25,
      "body_fat_percent": 17.9,
      "bmr": 1806,
      "inbody_score": 83,
      "visceral_fat_level": null
    },
    {
      "date": "2025-04-07",
      "weight": 80.2,
      "muscle_mass": 37.3,
      "fat_mass": 15.1,
      "bmi": 24.8,
      "body_fat_percent": 18.8,
      "bmr": 1776,
      "inbody_score": 81,
      "visceral_fat_level": null
    },
    {
      "date": "2025-04-19",
      "weight": 80.3,
      "muscle_mass": 37,
      "fat_mass": 15.5,
      "bmi": 24.8,
      "body_fat_percent": 19.2,
      "bmr": 1771,
      "inbody_score": 80,
      "visceral_fat_level": null
    },
    {
      "date": "2025-04-26",
      "weight": 80.6,
      "muscle_mass": 37.3,
      "fat_mass": 15.4,
      "bmi": 24.9,
      "body_fat_percent": 19,
      "bmr": 1779,
      "inbody_score": 81,
      "visceral_fat_level": null
    },
    {
      "date": "2025-05-04",
      "weight": 81,
      "muscle_mass": 37.9,
      "fat_mass": 14.7,
      "bmi": 25,
      "body_fat_percent": 18.2,
      "bmr": 1802,
      "inbody_score": 83,
      "visceral_fat_level": null
    },
    {
      "date": "2025-05-05",
      "weight": 81.5,
      "muscle_mass": 38.1,
      "fat_mass": 15,
      "bmi": 25.2,
      "body_fat_percent": 18.4,
      "bmr": 1806,
      "inbody_score": 83,
      "visceral_fat_level": null
    },
    {
      "date": "2025-05-19",
      "weight": 82.5,
      "muscle_mass": 37.7,
      "fat_mass": 16.6,
      "bmi": 25.5,
      "body_fat_percent": 20.1,
      "bmr": 1793,
      "inbody_score": 80,
      "visceral_fat_level": null
    },
    {
      "date": "2025-05-30",
      "weight": 81.6,
      "muscle_mass": 38.5,
      "fat_mass": 14.3,
      "bmi": 25.2,
      "body_fat_percent": 17.6,
      "bmr": 1823,
      "inbody_score": 84,
      "visceral_fat_level": null
    },
    {
      "date": "2025-06-12",
      "weight": 82.2,
      "muscle_mass": 38.6,
      "fat_mass": 14.7,
      "bmi": 25.4,
      "body_fat_percent": 17.9,
      "bmr": 1827,
      "inbody_score": 84,
      "visceral_fat_level": null
    },
    {
      "date": "2025-07-02",
      "weight": 83,
      "muscle_mass": 39.1,
      "fat_mass": 14.7,
      "bmi": 25.6,
      "body_fat_percent": 17.8,
      "bmr": 1844,
      "inbody_score": 85,
      "visceral_fat_level": null
    },
    {
      "date": "2025-07-17",
      "weight": 83.2,
      "muscle_mass": 39.4,
      "fat_mass": 14.4,
      "bmi": 25.7,
      "body_fat_percent": 17.3,
      "bmr": 1856,
      "inbody_score": 86,
      "visceral_fat_level": null
    },
    {
      "date": "2025-07-31",
      "weight": 82.4,
      "muscle_mass": 38.5,
      "fat_mass": 15.4,
      "bmi": 25.4,
      "body_fat_percent": 18.6,
      "bmr": 1818,
      "inbody_score": 83,
      "visceral_fat_level": null
    },
    {
      "date": "2025-08-20",
      "weight": 83.6,
      "muscle_mass": 39,
      "fat_mass": 15.2,
      "bmi": 25.8,
      "body_fat_percent": 18.2,
      "bmr": 1847,
      "inbody_score": 85,
      "visceral_fat_level": null
    },
    {
      "date": "2025-08-27",
      "weight": 84.3,
      "muscle_mass": 39.4,
      "fat_mass": 15.6,
      "bmi": 26,
      "body_fat_percent": 18.5,
      "bmr": 1854,
      "inbody_score": 85,
      "visceral_fat_level": null
    },
    {
      "date": "2025-09-05",
      "weight": 83.2,
      "muscle_mass": 38.9,
      "fat_mass": 15.2,
      "bmi": 25.7,
      "body_fat_percent": 18.3,
      "bmr": 1838,
      "inbody_score": 84,
      "visceral_fat_level": null
    },
    {
      "date": "2025-09-11",
      "weight": 83.4,
      "muscle_mass": 39.5,
      "fat_mass": 14.4,
      "bmi": 25.7,
      "body_fat_percent": 17.2,
      "bmr": 1861,
      "inbody_score": 86,
      "visceral_fat_level": null
    },
    {
      "date": "2025-09-28",
      "weight": 83.8,
      "muscle_mass": 39.2,
      "fat_mass": 15.4,
      "bmi": 25.9,
      "body_fat_percent": 18.4,
      "bmr": 1848,
      "inbody_score": 85,
      "visceral_fat_level": null
    },
    {
      "date": "2025-10-03",
      "weight": 83.4,
      "muscle_mass": 38.9,
      "fat_mass": 15.7,
      "bmi": 25.7,
      "body_fat_percent": 18.8,
      "bmr": 1832,
      "inbody_score": 83,
      "visceral_fat_level": null
    },
    {
      "date": "2025-10-12",
      "weight": 84.5,
      "muscle_mass": 39.5,
      "fat_mass": 15.7,
      "bmi": 26.1,
      "body_fat_percent": 18.6,
      "bmr": 1856,
      "inbody_score": 85,
      "visceral_fat_level": null
    },
    {
      "date": "2025-10-19",
      "weight": 85.1,
      "muscle_mass": 39.4,
      "fat_mass": 16.3,
      "bmi": 26.3,
      "body_fat_percent": 19.1,
      "bmr": 1856,
      "inbody_score": 84,
      "visceral_fat_level": null
    },
    {
      "date": "2025-11-02",
      "weight": 82.5,
      "muscle_mass": 37.9,
      "fat_mass": 16.3,
      "bmi": 25.5,
      "body_fat_percent": 19.7,
      "bmr": 1800,
      "inbody_score": 81,
      "visceral_fat_level": null
    },
    {
      "date": "2025-11-12",
      "weight": 85.9,
      "muscle_mass": 39.9,
      "fat_mass": 16.2,
      "bmi": 26.5,
      "body_fat_percent": 18.9,
      "bmr": 1875,
      "inbody_score": 85,
      "visceral_fat_level": null
    },
    {
      "date": "2025-11-16",
      "weight": 85,
      "muscle_mass": 39.4,
      "fat_mass": 16.3,
      "bmi": 26.2,
      "body_fat_percent": 19.2,
      "bmr": 1854,
      "inbody_score": null,
      "visceral_fat_level": null
    },
    {
      "date": "2025-11-22",
      "weight": 84.4,
      "muscle_mass": 39,
      "fat_mass": 16.5,
      "bmi": 26,
      "body_fat_percent": 19.5,
      "bmr": 1838,
      "inbody_score": 83,
      "visceral_fat_level": null
    },
    {
      "date": "2025-12-06",
      "weight": 84.2,
      "muscle_mass": 38.4,
      "fat_mass": 17.2,
      "bmi": 26,
      "body_fat_percent": 20.4,
      "bmr": 1818,
      "inbody_score": 81,
      "visceral_fat_level": null
    },
    {
      "date": "2025-12-18",
      "weight": 86.4,
      "muscle_mass": 39.4,
      "fat_mass": 17.3,
      "bmi": 26.7,
      "body_fat_percent": 20,
      "bmr": 1862,
      "inbody_score": 83,
      "visceral_fat_level": null
    },
    {
      "date": "2026-01-03",
      "weight": 84.6,
      "muscle_mass": 38.1,
      "fat_mass": 17.9,
      "bmi": 26.1,
      "body_fat_percent": 21.2,
      "bmr": 1811,
      "inbody_score": 80,
      "visceral_fat_level": null
    },
    {
      "date": "2026-01-10",
      "weight": 85.4,
      "muscle_mass": 39,
      "fat_mass": 17.3,
      "bmi": 26.4,
      "body_fat_percent": 20.3,
      "bmr": 1840,
      "inbody_score": 82,
      "visceral_fat_level": null
    },
    {
      "date": "2026-02-11",
      "weight": 85.1,
      "muscle_mass": 38,
      "fat_mass": 18.6,
      "bmi": 26.3,
      "body_fat_percent": 21.9,
      "bmr": 1806,
      "inbody_score": 79,
      "visceral_fat_level": null
    },
    {
      "date": "2026-02-21",
      "weight": 84.6,
      "muscle_mass": 38.7,
      "fat_mass": 17.2,
      "bmi": 26.1,
      "body_fat_percent": 20.3,
      "bmr": 1826,
      "inbody_score": 82,
      "visceral_fat_level": null
    },
    {
      "date": "2026-04-12",
      "weight": 85,
      "muscle_mass": 39.8,
      "fat_mass": 15.8,
      "bmi": 26.2,
      "body_fat_percent": 18.6,
      "bmr": 1865,
      "inbody_score": null,
      "visceral_fat_level": null
    },
    {
      "date": "2026-04-19",
      "weight": 84.1,
      "muscle_mass": 39.6,
      "fat_mass": 15.3,
      "bmi": 26,
      "body_fat_percent": 18.1,
      "bmr": 1857,
      "inbody_score": 85,
      "visceral_fat_level": null
    },
    {
      "date": "2026-04-26",
      "weight": 82.6,
      "muscle_mass": 38.3,
      "fat_mass": 15.7,
      "bmi": 25.5,
      "body_fat_percent": 19,
      "bmr": 1816,
      "inbody_score": 83,
      "visceral_fat_level": null
    }
  ]
}